pyPCR/Mep_panel.py
pyPCR/Rextractor.py
pyPCR/Threshold.xlsx
pyPCR/__init__.py
pyPCR/model.pkl
pyPCR-0.0.3.dist-info/LICENCE.txt
pyPCR-0.0.3.dist-info/METADATA
pyPCR-0.0.3.dist-info/WHEEL
pyPCR-0.0.3.dist-info/top_level.txt
pyPCR-0.0.3.dist-info/RECORD
