Metadata-Version: 2.1
Name: pyPCR
Version: 0.0.3
Summary: A library for processing and interpreting DNA high-resolution melt and amplification curves for the meningoencephalitis panel.
Home-page: https://github.com/PyPCR/PyPCR
License: MIT
Keywords: High Resolution Melt,Amplification Curve,Cycle threshold,PCR,rt-PCR,Meningoencephalitis,MEP,Pathogens
License-File: LICENCE.txt
Requires-Dist: fpdf ==1.7.2
Requires-Dist: matplotlib ==3.6.3
Requires-Dist: numpy ==1.23.5
Requires-Dist: pandas ==1.5.3
Requires-Dist: Pillow ==9.4.0
Requires-Dist: plotly ==5.13.1
Requires-Dist: scikit-learn ==1.4.1.post1
Requires-Dist: scipy ==1.13.0
